.editorconfig
.gitignore
.travis.yml
LICENSE
Makefile
README.rst
requirements-dev.txt
requirements.txt
setup.cfg
setup.py
data/config-example.ini
packaging/rpm/ttrss.spec
ttrss/.gitignore
ttrss/__init__.py
ttrss/__main__.py
ttrss/arguments.py
ttrss/article.py
ttrss/client.py
ttrss/config.py
ttrss/exception.py
ttrss/logging.py
ttrss/methods.py
ttrss/ttrss.py
ttrss/util.py
ttrss/version.py
ttrss.egg-info/PKG-INFO
ttrss.egg-info/SOURCES.txt
ttrss.egg-info/dependency_links.txt
ttrss.egg-info/entry_points.txt
ttrss.egg-info/requires.txt
ttrss.egg-info/top_level.txt