Metadata-Version: 1.2
Name: ttrss
Version: 1.1.5
Summary: A tool for synchronizing feeds from a Tiny Tiny RSS server.
Home-page: https://pypi.python.org/pypi/ttrss
Author: eikendev
Author-email: raphael@eiken.dev
License: MIT
Keywords: ttrss,feed,rss,atom,synchronize
Platform: UNKNOWN
Classifier: Development Status :: 4 - Beta
Classifier: Intended Audience :: Developers
Classifier: License :: OSI Approved :: MIT License
Classifier: Programming Language :: Python :: 3
Classifier: Topic :: Utilities
Classifier: Environment :: Console
Classifier: Operating System :: POSIX
Requires-Python: >=3
